LICENSE
README.md
setup.py
CVE_2024_1208.egg-info/PKG-INFO
CVE_2024_1208.egg-info/SOURCES.txt
CVE_2024_1208.egg-info/dependency_links.txt
CVE_2024_1208.egg-info/entry_points.txt
CVE_2024_1208.egg-info/requires.txt
CVE_2024_1208.egg-info/top_level.txt
cve20241208/__init__.py
cve20241208/main.py
cve20241208/includes/__init__.py
cve20241208/includes/bot.py
cve20241208/includes/filereader.py
cve20241208/includes/scan.py
cve20241208/includes/writefile.py
cve20241208/utils/__init__.py
cve20241208/utils/configure.py
cve20241208/utils/const.py
cve20241208/utils/helpers.py
cve20241208/utils/status.py